Metadata-Version: 2.1
Name: filebit
Version: 1.2.2
Summary: filebit python library and cli
Home-page: https://github.com/filebit/filebit-python
Author: filebit.net
Author-email: support@filebit.net
License: UNKNOWN
Platform: UNKNOWN
